{
  "hash": "5fff8d0e",
  "configHash": "f3a521a1",
  "lockfileHash": "af1289b3",
  "browserHash": "8198144a",
  "optimized": {
    "firebase/app": {
      "src": "../../node_modules/firebase/app/dist/esm/index.esm.js",
      "file": "firebase_app.js",
      "fileHash": "8e896c7e",
      "needsInterop": false
    },
    "firebase/auth": {
      "src": "../../node_modules/firebase/auth/dist/esm/index.esm.js",
      "file": "firebase_auth.js",
      "fileHash": "d39d7a0e",
      "needsInterop": false
    },
    "firebase/firestore": {
      "src": "../../node_modules/firebase/firestore/dist/esm/index.esm.js",
      "file": "firebase_firestore.js",
      "fileHash": "cda150ee",
      "needsInterop": false
    },
    "react-dom/client": {
      "src": "../../node_modules/react-dom/client.js",
      "file": "react-dom_client.js",
      "fileHash": "746eb740",
      "needsInterop": true
    },
    "react-router-dom": {
      "src": "../../node_modules/react-router-dom/dist/index.mjs",
      "file": "react-router-dom.js",
      "fileHash": "4fd0fd80",
      "needsInterop": false
    },
    "react": {
      "src": "../../node_modules/react/index.js",
      "file": "react.js",
      "fileHash": "4bc189b9",
      "needsInterop": true
    },
    "react/jsx-dev-runtime": {
      "src": "../../node_modules/react/jsx-dev-runtime.js",
      "file": "react_jsx-dev-runtime.js",
      "fileHash": "6b437782",
      "needsInterop": true
    },
    "recharts": {
      "src": "../../node_modules/recharts/es6/index.js",
      "file": "recharts.js",
      "fileHash": "ce49d80b",
      "needsInterop": false
    }
  },
  "chunks": {
    "index.esm-Rr-3tvL0": {
      "file": "index.esm-Rr-3tvL0.js",
      "isDynamicEntry": false
    },
    "react-CZunmVaX": {
      "file": "react-CZunmVaX.js",
      "isDynamicEntry": false
    },
    "react-dom-DlAeUGhR": {
      "file": "react-dom-DlAeUGhR.js",
      "isDynamicEntry": false
    }
  }
}